[ { "domain":"dlya.top","subject":"CN=dlya.top","start":"Feb 27 02:31:59 2022 GMT","expire":"May 28 02:31:58 2022 GMT","issuer":"C=US; O=Let's Encrypt; CN=R3","status":"有效","statuscolor":"success","check":"2022-03-24 00:26:52","remain":"65"},{"domain":"www.dlya.top","subject":"CN=www.dlya.top","start":"Feb 27 02:32:04 2022 GMT","expire":"May 28 02:32:03 2022 GMT","issuer":"C=US; O=Let's Encrypt; CN=R3","status":"有效","statuscolor":"success","check":"2022-03-24 00:26:52","remain":"65"},{"domain":"blog.dlya.top","subject":"C=US; ST=California; L=San Francisco; O=Cloudflare, Inc.; CN=sni.cloudflaressl.com","start":"Feb 27 00:00:00 2022 GMT","expire":"Feb 27 23:59:59 2023 GMT","issuer":"C=US; O=Cloudflare, Inc.; CN=Cloudflare Inc ECC CA-3","status":"有效","statuscolor":"success","check":"2022-03-24 00:26:53","remain":"341"},{"domain":"status.dlya.top","subject":"","start":"","expire":"","issuer":"","status":"失效","statuscolor":"error","check":"2022-03-24 00:28:08","remain":"0"},{"domain":"playing.dlya.top","subject":"C=US; ST=California; L=San Francisco; O=Cloudflare, Inc.; CN=playing.dlya.top","start":"Feb 27 00:00:00 2022 GMT","expire":"Feb 26 23:59:59 2023 GMT","issuer":"C=US; O=Cloudflare, Inc.; CN=Cloudflare Inc ECC CA-3","status":"有效","statuscolor":"success","check":"2022-03-24 00:28:08","remain":"340"},{"domain":"ssl.dlya.top","subject":"C=US; ST=California; L=San Francisco; O=Cloudflare, Inc.; CN=ssl.dlya.top","start":"Feb 27 00:00:00 2022 GMT","expire":"Feb 26 23:59:59 2023 GMT","issuer":"C=US; O=Cloudflare, Inc.; CN=Cloudflare Inc ECC CA-3","status":"有效","statuscolor":"success","check":"2022-03-24 00:28:09","remain":"340"},{"domain":"pan.dlya.top","subject":"C=US; ST=California; L=San Francisco; O=Cloudflare, Inc.; CN=sni.cloudflaressl.com","start":"Feb 27 00:00:00 2022 GMT","expire":"Feb 27 23:59:59 2023 GMT","issuer":"C=US; O=Cloudflare, Inc.; CN=Cloudflare Inc ECC CA-3","status":"有效","statuscolor":"success","check":"2022-03-24 00:28:09","remain":"341"},{"domain":"fownhost.ga","subject":"C=US; ST=California; L=San Francisco; O=Cloudflare, Inc.; CN=sni.cloudflaressl.com","start":"Aug 26 00:00:00 2021 GMT","expire":"Aug 25 23:59:59 2022 GMT","issuer":"C=US; O=Cloudflare, Inc.; CN=Cloudflare Inc ECC CA-3","status":"有效","statuscolor":"success","check":"2022-03-24 00:28:11","remain":"155"},{"domain":"fownhost.gq","subject":"C=US; ST=California; L=San Francisco; O=Cloudflare, Inc.; CN=sni.cloudflaressl.com","start":"Aug 26 00:00:00 2021 GMT","expire":"Aug 25 23:59:59 2022 GMT","issuer":"C=US; O=Cloudflare, Inc.; CN=Cloudflare Inc ECC CA-3","status":"有效","statuscolor":"success","check":"2022-03-24 00:28:13","remain":"155"},{"domain":"fownhost.ml","subject":"C=US; ST=California; L=San Francisco; O=Cloudflare, Inc.; CN=sni.cloudflaressl.com","start":"Aug 26 00:00:00 2021 GMT","expire":"Aug 25 23:59:59 2022 GMT","issuer":"C=US; O=Cloudflare, Inc.; CN=Cloudflare Inc ECC CA-3","status":"有效","statuscolor":"success","check":"2022-03-24 00:28:14","remain":"155"},{"domain":"fownhost.tk","subject":"C=US; ST=California; L=San Francisco; O=Cloudflare, Inc.; CN=sni.cloudflaressl.com","start":"Aug 26 00:00:00 2021 GMT","expire":"Aug 25 23:59:59 2022 GMT","issuer":"C=US; O=Cloudflare, Inc.; CN=Cloudflare Inc ECC CA-3","status":"有效","statuscolor":"success","check":"2022-03-24 00:28:16","remain":"155"},{"domain":"cpanel.fownhost.ga","subject":"CN=cpanel.fownhost.ga","start":"Jan 28 09:27:30 2022 GMT","expire":"Apr 28 09:27:29 2022 GMT","issuer":"C=US; O=Let's Encrypt; CN=R3","status":"有效","statuscolor":"success","check":"2022-03-24 00:28:16","remain":"35" } ]
