[ { "domain":"dlya.top","subject":"CN=dlya.top","start":"Jan 28 17:59:50 2023 GMT","expire":"Apr 28 17:59:49 2023 GMT","issuer":"C=US; O=Let's Encrypt; CN=R3","status":"无效","statuscolor":"error","check":"2023-02-06 00:20:37","remain":"82"},{"domain":"www.dlya.top","subject":"CN=www.dlya.top","start":"Jan 20 07:07:03 2023 GMT","expire":"Apr 20 07:07:02 2023 GMT","issuer":"C=US; O=Let's Encrypt; CN=R3","status":"无效","statuscolor":"error","check":"2023-02-06 00:20:41","remain":"73"},{"domain":"blog.dlya.top","subject":"CN=blog.dlya.top","start":"Jan 4 07:42:37 2023 GMT","expire":"Apr 4 07:42:36 2023 GMT","issuer":"C=US; O=Let's Encrypt; CN=R3","status":"无效","statuscolor":"error","check":"2023-02-06 00:20:42","remain":"57"},{"domain":"ssl.dlya.top","subject":"C=US; ST=California; L=San Francisco; O=Cloudflare, Inc.; CN=ssl.dlya.top","start":"Jan 27 00:00:00 2023 GMT","expire":"Jan 26 23:59:59 2024 GMT","issuer":"C=US; O=Cloudflare, Inc.; CN=Cloudflare Inc ECC CA-3","status":"无效","statuscolor":"error","check":"2023-02-06 00:20:42","remain":"355"},{"domain":"cdn.dlya.top","subject":"CN=cdn.dlya.top","start":"Dec 12 12:21:54 2022 GMT","expire":"Mar 12 12:21:53 2023 GMT","issuer":"C=US; O=Let's Encrypt; CN=R3","status":"无效","statuscolor":"error","check":"2023-02-06 00:20:42","remain":"34"},{"domain":"static.dlya.top","subject":"C=US; ST=California; L=San Francisco; O=Cloudflare, Inc.; CN=sni.cloudflaressl.com","start":"Jan 28 00:00:00 2023 GMT","expire":"Jan 27 23:59:59 2024 GMT","issuer":"C=US; O=Cloudflare, Inc.; CN=Cloudflare Inc ECC CA-3","status":"无效","statuscolor":"error","check":"2023-02-06 00:20:43","remain":"356"},{"domain":"file.dlya.top","subject":"C=US; ST=California; L=San Francisco; O=Cloudflare, Inc.; CN=sni.cloudflaressl.com","start":"Jan 28 00:00:00 2023 GMT","expire":"Jan 27 23:59:59 2024 GMT","issuer":"C=US; O=Cloudflare, Inc.; CN=Cloudflare Inc ECC CA-3","status":"无效","statuscolor":"error","check":"2023-02-06 00:20:43","remain":"356"},{"domain":"avatar.dlya.top","subject":"CN=avatar.dlya.top","start":"Dec 22 01:16:25 2022 GMT","expire":"Mar 22 01:16:24 2023 GMT","issuer":"C=US; O=Let's Encrypt; CN=R3","status":"无效","statuscolor":"error","check":"2023-02-06 00:20:43","remain":"44"},{"domain":"pan.dlya.top","subject":"CN=pan.dlya.top","start":"Jan 26 15:25:50 2023 GMT","expire":"Apr 26 15:25:49 2023 GMT","issuer":"C=US; O=Let's Encrypt; CN=R3","status":"无效","statuscolor":"error","check":"2023-02-06 00:20:59","remain":"79"},{"domain":"playing.dlya.top","subject":"","start":"","expire":"","issuer":"","status":"失效","statuscolor":"error","check":"2023-02-06 00:21:00","remain":"0"},{"domain":"waline.dlya.top","subject":"","start":"","expire":"","issuer":"","status":"失效","statuscolor":"error","check":"2023-02-06 00:21:00","remain":"0" } ]
